bin/concrt140.dll
bin/mmg.dll
bin/mmg2d.dll
bin/mmg2d_O3.exe
bin/mmg3d.dll
bin/mmg3d_O3.exe
bin/mmgs.dll
bin/mmgs_O3.exe
bin/msvcp140.dll
bin/msvcp140_1.dll
bin/msvcp140_2.dll
bin/msvcp140_atomic_wait.dll
bin/msvcp140_codecvt_ids.dll
bin/vcruntime140.dll
bin/vcruntime140_1.dll
bin/__init__.py
include/__init__.py
include/mmg/libmmg.h
include/mmg/libmmgf.h
include/mmg/common/libmmgtypes.h
include/mmg/common/libmmgtypesf.h
include/mmg/common/mmgcmakedefines.h
include/mmg/common/mmgcmakedefinesf.h
include/mmg/common/mmgversion.h
include/mmg/common/mmg_export.h
include/mmg/mmg2d/libmmg2d.h
include/mmg/mmg2d/libmmg2df.h
include/mmg/mmg2d/mmg2d_export.h
include/mmg/mmg3d/libmmg3d.h
include/mmg/mmg3d/libmmg3df.h
include/mmg/mmg3d/mmg3d_export.h
include/mmg/mmgs/libmmgs.h
include/mmg/mmgs/libmmgsf.h
include/mmg/mmgs/mmgs_export.h
lib/mmg.lib
lib/mmg2d.lib
lib/mmg3d.lib
lib/mmgs.lib
lib/__init__.py
lib/cmake/mmg/FindElas.cmake
lib/cmake/mmg/FindSCOTCH.cmake
lib/cmake/mmg/mmgConfig.cmake
lib/cmake/mmg/MmgTargets-release.cmake
lib/cmake/mmg/MmgTargets.cmake
mmgpy/lagrangian.py
mmgpy/metrics.py
mmgpy/mmg2d.dll
mmgpy/mmg2d.lib
mmgpy/mmg3d.dll
mmgpy/mmg3d.lib
mmgpy/mmgs.dll
mmgpy/mmgs.lib
mmgpy/progress.py
mmgpy/py.typed
mmgpy/sizing.py
mmgpy/_io.py
mmgpy/_logging.py
mmgpy/_mesh.py
mmgpy/_mmgpy.cp311-win_amd64.pyd
mmgpy/_mmgpy.pyi
mmgpy/_options.py
mmgpy/_progress.py
mmgpy/_pyvista.py
mmgpy/_result.py
mmgpy/_transfer.py
mmgpy/_validation.py
mmgpy/_version.py
mmgpy/_version.py.in
mmgpy/__init__.py
mmgpy/__main__.py
mmgpy/bin/mmg2d.dll
mmgpy/bin/mmg3d.dll
mmgpy/bin/mmgs.dll
mmgpy/bin/Release/mmg2d_O3.exe
mmgpy/bin/Release/mmg3d_O3.exe
mmgpy/bin/Release/mmgs_O3.exe
mmgpy/interactive/sizing_editor.py
mmgpy/interactive/__init__.py
mmgpy/repair/_core.py
mmgpy/repair/_elements.py
mmgpy/repair/_vertices.py
mmgpy/repair/__init__.py
mmgpy/ui/app.py
mmgpy/ui/parsers.py
mmgpy/ui/remeshing.py
mmgpy/ui/samples.py
mmgpy/ui/utils.py
mmgpy/ui/viewer.py
mmgpy/ui/__init__.py
mmgpy/ui/__main__.py
mmgpy-0.5.2.dist-info/DELVEWHEEL
mmgpy-0.5.2.dist-info/entry_points.txt
mmgpy-0.5.2.dist-info/METADATA
mmgpy-0.5.2.dist-info/RECORD
mmgpy-0.5.2.dist-info/WHEEL
mmgpy-0.5.2.dist-info/licenses/LICENSE
