Metadata-Version: 2.2
Name: mmgpy
Version: 0.5.2
Summary: Python bindings for the MMG software
Author-Email: Kevin Marchais <kevinmarchais@gmail.com>
License: MIT
Classifier: Development Status :: 4 - Beta
Classifier: Intended Audience :: Developers
Classifier: License :: OSI Approved :: MIT License
Classifier: Programming Language :: Python :: 3
Classifier: Programming Language :: Python :: 3.10
Classifier: Programming Language :: Python :: 3.11
Classifier: Programming Language :: Python :: 3.12
Classifier: Programming Language :: Python :: 3.13
Requires-Python: >=3.10
Requires-Dist: meshio>=5.3.5
Requires-Dist: numpy>=2.0.2
Requires-Dist: patchelf>=0.17.2.4; sys_platform == "linux"
Requires-Dist: pyvista>=0.46.4
Requires-Dist: rich>=13.0.0
Requires-Dist: scipy<1.17,>=1.11.0
Requires-Dist: typing-extensions>=4.0.0; python_version < "3.11"
Provides-Extra: ui
Requires-Dist: pywebview>=6.1; extra == "ui"
Requires-Dist: trame>=3.12.0; extra == "ui"
Requires-Dist: trame-vtk>=2.10.2; extra == "ui"
Requires-Dist: trame-vtklocal>=0.16.0; extra == "ui"
Requires-Dist: trame-vuetify>=3.2.0; extra == "ui"
